AsteriskChannelHangup
