Metadata-Version: 1.0
Name: AsteriskChannelHangup
Version: 0.0.2
Summary: Programa utilizado para prevenir canales colgados en una planta asterisk
Home-page: http://www.sapian.com.co
Author: Sebastian rojo
Author-email: srojo@sapian.com.co
License: GPL
Platform: UNKNOWN
